adafruit_as726x.py
adafruit_circuitpython_as726x-2.0.23.dist-info/licenses/LICENSE
adafruit_circuitpython_as726x-2.0.23.dist-info/METADATA
adafruit_circuitpython_as726x-2.0.23.dist-info/WHEEL
adafruit_circuitpython_as726x-2.0.23.dist-info/top_level.txt
adafruit_circuitpython_as726x-2.0.23.dist-info/RECORD
